datascience_toolkits/__init__.py
datascience_toolkits/_nbdev.py
datascience_toolkits/core.py
datascience_toolkits/env.py
datascience_toolkits/env_init.py
datascience_toolkits/experimental.py
datascience_toolkits/template.py
datascience_toolkits/.ipynb_checkpoints/env-checkpoint.py
datascience_toolkits/.ipynb_checkpoints/env_init-checkpoint.py
datascience_toolkits-0.0.8.dist-info/LICENSE
datascience_toolkits-0.0.8.dist-info/METADATA
datascience_toolkits-0.0.8.dist-info/WHEEL
datascience_toolkits-0.0.8.dist-info/entry_points.txt
datascience_toolkits-0.0.8.dist-info/top_level.txt
datascience_toolkits-0.0.8.dist-info/RECORD
