Metadata-Version: 2.1
Name: datascience-toolkits
Version: 0.0.8
Summary: A package containing some handy and useful modules for practical data science.
Home-page: https://github.com/leemengtaiwan/datascience_toolkits
Author: LeeMeng
Author-email: b98705001@gmail.com
License: Apache Software License 2.0
Keywords: python datascience_toolkits
Platform: UNKNOWN
Classifier: Development Status :: 3 - Alpha
Classifier: Intended Audience :: Developers
Classifier: License :: OSI Approved :: Apache Software License
Classifier: Natural Language :: English
Classifier: Programming Language :: Python :: 3.6
Classifier: Programming Language :: Python :: 3.7
Classifier: Programming Language :: Python :: 3.8
Requires-Python: >=3.6
Requires-Dist: pandas
Requires-Dist: scikit-learn
Requires-Dist: gensim
Requires-Dist: nltk
Requires-Dist: tensorflow
Requires-Dist: tqdm
Requires-Dist: transformers
Requires-Dist: simpletransformers
Requires-Dist: chartify
Requires-Dist: swifter
Requires-Dist: matplotlib
Requires-Dist: seaborn
Requires-Dist: pendulum
